{
  "db_name": "PostgreSQL",
  "query": "INSERT INTO tournaments (startgg_id, name, handle, online, city, addr_state)\n         VALUES (9001, 'LACS', 'tournament/lacs', false, 'Los Angeles', 'CA')\n         RETURNING id",
  "describe": {
    "columns": [
      {
        "ordinal": 0,
        "name": "id",
        "type_info": "Uuid"
      }
    ],
    "parameters": {
      "Left": []
    },
    "nullable": [
      false
    ]
  },
  "hash": "e5cbb2295db21cfdafb05e8acb7f5fc1e07fb92ad15fd7243293e08b3e3aee88"
}
